ziobro/__init__.py
ziobro/const.py
ziobro/exit.py
ziobro/func.py
ziobro/object.py
ziobro-0.0.0.dist-info/LICENSE
ziobro-0.0.0.dist-info/METADATA
ziobro-0.0.0.dist-info/WHEEL
ziobro-0.0.0.dist-info/top_level.txt
ziobro-0.0.0.dist-info/RECORD
